plasmith/__init__.py
plasmith-0.1.0.dist-info/METADATA
plasmith-0.1.0.dist-info/WHEEL
plasmith-0.1.0.dist-info/top_level.txt
plasmith-0.1.0.dist-info/RECORD
